frcstreamer
venv
