Metadata-Version: 1.0
Name: frcstreamer
Version: 1.0.2
Summary: A package to get FRC streams
Home-page: https://github.com/tweirtx/frcstreamer
Author: Travis Weir
Author-email: tweirtx@gmail.com
License: Apache 2.0
Platform: UNKNOWN
